[
   {
        "nome": "Copa D'Or",
        "status": "calibragem",
        "pacientes": "23/70"
    },
    {
        "nome": "CDPI",
        "status": "relatório",
        "pacientes": "52/80"
    },
     {
        "nome": "Barra D'Or",
        "status": "calibragem",
        "pacientes": "69/90"
    },
    {
        "nome": "Miguel Couto",
        "status": "finalizado",
        "pacientes": "70/70"
    },
    {
        "nome": "Americas",
        "status": "backlog",
        "pacientes": "0/30"
    }
]